{
  "usuariosCadastrados": [
    {
      "id": 1,
      "nome": "Isabelle Vitoria",
      "sexo": "Feminino",
      "cpf": "39199543032",
      "dataNascimento": "29/10/2016",
      "email": "isavitoria@email.com",
      "senha": "isa446578",
      "endereco": ""
    },
    {
      "id": 2,
      "nome": "Ryan Fabricio",
      "sexo": "Masculino",
      "cpf": "09453168017",
      "dataNascimento": "05/07/1990",
      "email": "ryanfabricio@email.com",
      "senha": "26121990",
      "endereco": ""
    },
    {
      "id": 3,
      "nome": "Miguel Vieira",
      "sexo": "Masculino",
      "cpf": "44253186092",
      "dataNascimento": "22/11/2021",
      "email": "isavitoria@email.com",
      "senha": "viera391",
      "endereco": ""
    },
    {
      "id": 4,
      "nome": "Edite Rosa",
      "sexo": "Feminino",
      "cpf": "41786468000",
      "dataNascimento": "20/10/1965",
      "email": "edite2008@email.com",
      "senha": "18012000",
      "endereco": ""
    },
    {
      "id": 5,
      "nome": "Eduardo Martins",
      "sexo": "Masculino",
      "cpf": "39146690042",
      "dataNascimento": "25/10/2000",
      "email": "edumartins@gamil.com",
      "senha": "78453612",
      "endereco": ""
    },
    {
      "id": 6,
      "nome": "Leonardo Golcalves",
      "sexo": "Masculino",
      "cpf": "01898631026",
      "dataNascimento": "18/01/1999",
      "email": "isavitoria@email.com",
      "senha": "5958leog",
      "endereco": ""
    }
  ],
  "locaisColeta": [
    {
      "id": "1",
      "nomeLocal": "ponto coleta",
      "descricao": "",
      "cep": "88060284",
      "logradouro": "Servid찾o Antonia Castro Garcia",
      "numero": "",
      "complemento": "",
      "bairro": "S찾o Jo찾o do Rio Vermelho",
      "estado": "SC",
      "cidade": "Florian처polis",
      "longitude": "",
      "latitude": "",
      "vidro": false,
      "metal": true,
      "papel": false,
      "plastico": false,
      "organico": false,
      "baterias": false,
      "outros": false
    }
  ]
}